sgs/__init__.py
sgs/__version__.py
sgs/api.py
sgs/common.py
sgs/dataframe.py
sgs/metadata.py
sgs/search.py
sgs/ts.py
sgs-3.0.0.dist-info/licenses/LICENSE
sgs-3.0.0.dist-info/METADATA
sgs-3.0.0.dist-info/WHEEL
sgs-3.0.0.dist-info/top_level.txt
sgs-3.0.0.dist-info/RECORD
