Metadata-Version: 2.4
Name: sgs
Version: 3.0.0
Summary: Python wrapper para o webservice do SGS - Sistema Gerenciador de Series Temporais do Banco Central do Brasil.
Home-page: https://github.com/rafpyprog/pySGS
Author: Rafael Alves Ribeiro
Author-email: rafael.alves.ribeiro@gmail.com
License: MIT
Classifier: Development Status :: 4 - Beta
Classifier: Intended Audience :: Developers
Classifier: Intended Audience :: Science/Research
Classifier: License :: OSI Approved :: MIT License
Classifier: Programming Language :: Python :: 3.9
Classifier: Programming Language :: Python :: 3.10
Classifier: Programming Language :: Python :: 3.11
Classifier: Programming Language :: Python :: 3.12
Classifier: Programming Language :: Python :: 3.13
Classifier: Topic :: Scientific/Engineering :: Information Analysis
Requires-Python: >=3.6
License-File: LICENSE
Requires-Dist: beautifulsoup4>=4.7.1
Requires-Dist: html5lib>=1.0.1
Requires-Dist: pandas>=0.24.2
Requires-Dist: retrying>=1.3.3
Requires-Dist: requests>=2.22.0
Provides-Extra: dev
Requires-Dist: bandit>=1.6.0; extra == "dev"
Requires-Dist: codecov>=2.0.15; extra == "dev"
Requires-Dist: mypy>=0.910; extra == "dev"
Requires-Dist: pytest>=4.6.2; extra == "dev"
Requires-Dist: pytest-cov>=2.7.1; extra == "dev"
Requires-Dist: pytest-mypy>=0.8.1; extra == "dev"
Requires-Dist: types-requests>=2.25.6; extra == "dev"
Dynamic: author
Dynamic: author-email
Dynamic: classifier
Dynamic: description
Dynamic: home-page
Dynamic: license
Dynamic: license-file
Dynamic: provides-extra
Dynamic: requires-dist
Dynamic: requires-python
Dynamic: summary
